spark_tts_mcp/__init__.py
spark_tts_mcp/__main__.py
spark_tts_mcp/comfyui_client.py
spark_tts_mcp/server.py
spark_tts_mcp/workflows/spark-tts.json
spark_tts_mcp-0.1.4.dist-info/licenses/LICENSE
spark_tts_mcp-0.1.4.dist-info/METADATA
spark_tts_mcp-0.1.4.dist-info/WHEEL
spark_tts_mcp-0.1.4.dist-info/entry_points.txt
spark_tts_mcp-0.1.4.dist-info/top_level.txt
spark_tts_mcp-0.1.4.dist-info/RECORD
