Metadata-Version: 2.4
Name: spark-tts-mcp
Version: 0.1.4
Summary: MCP Server to generate speech using a local ComfyUI instance with SparkTTS.
Author-email: Your Name <your.email@example.com>
License: MIT License
Classifier: Programming Language :: Python :: 3
Classifier: License :: OSI Approved :: MIT License
Classifier: Operating System :: OS Independent
Classifier: Development Status :: 3 - Alpha
Classifier: Intended Audience :: Developers
Classifier: Topic :: Scientific/Engineering :: Artificial Intelligence
Classifier: Topic :: Software Development :: Libraries :: Python Modules
Requires-Python: >=3.9
License-File: LICENSE
Requires-Dist: httpx
Requires-Dist: mcp[cli]
Requires-Dist: websocket-client
Requires-Dist: aiohttp
Requires-Dist: aiofiles
Requires-Dist: pydantic
Dynamic: license-file
